README.txt
plonetheme.blueblog-configure.zcml
setup.cfg
setup.py
docs/HISTORY.txt
docs/INSTALL.txt
docs/LICENSE.GPL
docs/LICENSE.txt
plonetheme/__init__.py
plonetheme.blueblog.egg-info/PKG-INFO
plonetheme.blueblog.egg-info/SOURCES.txt
plonetheme.blueblog.egg-info/dependency_links.txt
plonetheme.blueblog.egg-info/entry_points.txt
plonetheme.blueblog.egg-info/namespace_packages.txt
plonetheme.blueblog.egg-info/not-zip-safe
plonetheme.blueblog.egg-info/requires.txt
plonetheme.blueblog.egg-info/top_level.txt
plonetheme/blueblog/__init__.py
plonetheme/blueblog/configure.zcml
plonetheme/blueblog/profiles.zcml
plonetheme/blueblog/setuphandlers.py
plonetheme/blueblog/skins.zcml
plonetheme/blueblog/tests.py
plonetheme/blueblog/version.txt
plonetheme/blueblog/browser/__init__.py
plonetheme/blueblog/browser/configure.zcml
plonetheme/blueblog/browser/interfaces.py
plonetheme/blueblog/browser/viewlet.pt
plonetheme/blueblog/browser/viewlets.py
plonetheme/blueblog/browser/images/articlebg.gif
plonetheme/blueblog/browser/images/bg.gif
plonetheme/blueblog/browser/images/h2bg.gif
plonetheme/blueblog/browser/images/header.gif
plonetheme/blueblog/browser/images/horizontal.gif
plonetheme/blueblog/browser/images/horizontal.jpg
plonetheme/blueblog/browser/images/menutop.gif
plonetheme/blueblog/browser/images/searchbox.gif
plonetheme/blueblog/browser/images/sidebar.gif
plonetheme/blueblog/browser/stylesheets/main.css
plonetheme/blueblog/browser/templates/global_logo.pt
plonetheme/blueblog/profiles/default/cssregistry.xml
plonetheme/blueblog/profiles/default/import_steps.xml
plonetheme/blueblog/profiles/default/jsregistry.xml
plonetheme/blueblog/profiles/default/plonetheme.blueblog_various.txt
plonetheme/blueblog/profiles/default/skins.xml
plonetheme/blueblog/profiles/default/viewlets.xml
plonetheme/blueblog/skins/plonetheme_blueblog_custom_images/articlebg.gif
plonetheme/blueblog/skins/plonetheme_blueblog_custom_images/bg.gif
plonetheme/blueblog/skins/plonetheme_blueblog_custom_images/h2bg.gif
plonetheme/blueblog/skins/plonetheme_blueblog_custom_images/header.gif
plonetheme/blueblog/skins/plonetheme_blueblog_custom_images/horizontal.gif
plonetheme/blueblog/skins/plonetheme_blueblog_custom_images/horizontal.jpg
plonetheme/blueblog/skins/plonetheme_blueblog_custom_images/menutop.gif
