Metadata-Version: 1.0
Name: plonetheme.blueblog
Version: 0.1dev-r60738
Summary: An installable theme for Plone 3.0
Home-page: http://svn.plone.org/svn/collective/
Author: Jan Filip Tristan Hasecke
Author-email: blenderkid@web.de
License: GPL
Keywords: web zope plone theme
Platform: UNKNOWN
Classifier: Framework :: Plone
Classifier: Framework :: Zope2
Classifier: Framework :: Zope3
Classifier: Programming Language :: Python
Classifier: Topic :: Software Development :: Libraries :: Python Modules
